setup.py
incywincy/__init__.py
incywincy/config.py
incywincy/http.py
incywincy/report.py
incywincy/sample_settings.py
incywincy/spider.py
incywincy/visitors.py
incywincy.egg-info/PKG-INFO
incywincy.egg-info/SOURCES.txt
incywincy.egg-info/dependency_links.txt
incywincy.egg-info/requires.txt
incywincy.egg-info/top_level.txt