Metadata-Version: 1.1
Name: incywincy
Version: 0.2.0
Summary: Web Spider Testing Framework
Home-page: https://github.com/txels/incywincy
Author: Carles Barrobés
Author-email: carles@barrobes.com
License: UNKNOWN
Platform: UNKNOWN
Classifier: Development Status :: 4 - Beta
Classifier: Intended Audience :: Developers
Classifier: License :: OSI Approved :: GNU Library or Lesser General Public License (LGPL)
Classifier: Operating System :: OS Independent
Classifier: Programming Language :: Python
Classifier: Topic :: Software Development :: Testing
